snapdiff/__init__.py
snapdiff/deepdiff_custom.py
snapdiff/invoke_utils.py
snapdiff/snapper.py
snapdiff/tasks.py
snapdiff/utils.py
snapdiff-0.1.2.data/data/requirements.txt
snapdiff-0.1.2.dist-info/LICENSE
snapdiff-0.1.2.dist-info/METADATA
snapdiff-0.1.2.dist-info/WHEEL
snapdiff-0.1.2.dist-info/top_level.txt
snapdiff-0.1.2.dist-info/RECORD
