Metadata-Version: 2.1
Name: snapdiff
Version: 0.1.2
Summary: A package for comparing snapshots of data and tracking differences when function change
Home-page: https://github.com/ahmedhendy/snapdiff
Author: Ahmed Hendy
Author-email: ahmedelsyd5@gmail.com
Classifier: Programming Language :: Python :: 3
Classifier: License :: OSI Approved :: MIT License
Classifier: Operating System :: OS Independent
Requires-Python: >=3.7
License-File: LICENSE
Requires-Dist: deepdiff
Requires-Dist: joblib
Requires-Dist: pyyaml
Requires-Dist: astor
Requires-Dist: invoke
Requires-Dist: pydantic
